[
{
  "Denominazione": "ARGONAUTI-le dimore di talos",
  "CIS": "BA07203891000017769",
  "Tipologia": "Alloggi privati",
  "Sottotipologia": "Locazione turistica",
  "Provincia": "BA",
  "Comune": "RUVO DI PUGLIA",
  "CAP": "70037",
  "Localita'": "ruvo di puglia",
  "Via": "VIA AVITAJA ",
  "Civico": "30"
},
{
  "Denominazione": "Affittacamere ",
  "CIS": "BA07203891000029948",
  "Tipologia": "Alloggi privati",
  "Sottotipologia": "Locazione turistica",
  "Provincia": "BA",
  "Comune": "RUVO DI PUGLIA",
  "CAP": "70037",
  "Localita'": "Ruvo di Puglia ",
  "Via": "Via don Pietro pappagallo ",
  "Civico": "45"
},
{
  "Denominazione": "Alibi Suites (Casa Vacanze Piazza Bovio)",
  "CIS": "BA07203891000031276",
  "Tipologia": "Alloggi privati",
  "Sottotipologia": "Locazione turistica",
  "Provincia": "BA",
  "Comune": "RUVO DI PUGLIA",
  "CAP": "70037",
  "Localita'": "Ruvo di Puglia",
  "Via": "Piazza Bovio ",
  "Civico": "26"
},
{
  "Denominazione": "Alibi Suites SPA (CASA VACANZE FIERAMOSCA)",
  "CIS": "BA07203891000030920",
  "Tipologia": "Alloggi privati",
  "Sottotipologia": "Locazione turistica",
  "Provincia": "BA",
  "Comune": "RUVO DI PUGLIA",
  "CAP": "70037",
  "Localita'": "RUVO DI PUGLIA",
  "Via": "VIA ETTORE FIERAMOSCA",
  "Civico": "57"
},
{
  "Denominazione": "B&B da Francesco",
  "CIS": "BA07203891000033333",
  "Tipologia": "Alloggi privati",
  "Sottotipologia": "Locazione turistica",
  "Provincia": "BA",
  "Comune": "RUVO DI PUGLIA",
  "CAP": "70037",
  "Localita'": "RUVO DI PUGLIA",
  "Via": "ZONA RURALE",
  "Civico": "93"
},
{
  "Denominazione": "Bella Vita",
  "CIS": "BA07203891000006121",
  "Tipologia": "Alloggi privati",
  "Sottotipologia": "Locazione turistica",
  "Provincia": "BA",
  "Comune": "RUVO DI PUGLIA",
  "CAP": "70037",
  "Localita'": "Ruvo Di Puglia",
  "Via": "Via Imbriani ",
  "Civico": "16"
},
{
  "Denominazione": "Carafa61",
  "CIS": "BA07203891000030877",
  "Tipologia": "Alloggi privati",
  "Sottotipologia": "Locazione turistica",
  "Provincia": "BA",
  "Comune": "RUVO DI PUGLIA",
  "CAP": "70037",
  "Localita'": "Ruvo di Puglia",
  "Via": "Corso Carafa",
  "Civico": "61"
},
{
  "Denominazione": "Coming Suite & Spa",
  "CIS": "BA07203891000039715",
  "Tipologia": "Alloggi privati",
  "Sottotipologia": "Locazione turistica",
  "Provincia": "BA",
  "Comune": "RUVO DI PUGLIA",
  "CAP": "70037",
  "Localita'": "Ruvo di Puglia",
  "Via": "Via Duca della Vittoria ",
  "Civico": "45"
},
{
  "Denominazione": "Fa.R\u00f2. Dimora",
  "CIS": "BA07203891000041261",
  "Tipologia": "Alloggi privati",
  "Sottotipologia": "Locazione turistica",
  "Provincia": "BA",
  "Comune": "RUVO DI PUGLIA",
  "CAP": "70037",
  "Localita'": "Ruvo di puglia",
  "Via": "via cirillo ",
  "Civico": "97"
},
{
  "Denominazione": "HOME CHLOE",
  "CIS": "BA07203891000023465",
  "Tipologia": "Alloggi privati",
  "Sottotipologia": "Locazione turistica",
  "Provincia": "BA",
  "Comune": "RUVO DI PUGLIA",
  "CAP": "70037",
  "Via": "VIA LORIA ",
  "Civico": "8"
},
{
  "Denominazione": "HOME LUNA",
  "CIS": "BA07203891000034723",
  "Tipologia": "Alloggi privati",
  "Sottotipologia": "Locazione turistica",
  "Provincia": "BA",
  "Comune": "RUVO DI PUGLIA",
  "CAP": "70037",
  "Localita'": "RUVO DI PUGLIA",
  "Via": "VICO IV SANTA BARBARA ",
  "Civico": "6"
},
{
  "Denominazione": "HOME STELLA",
  "CIS": "BA07203891000034724",
  "Tipologia": "Alloggi privati",
  "Sottotipologia": "Locazione turistica",
  "Provincia": "BA",
  "Comune": "RUVO DI PUGLIA",
  "CAP": "70037",
  "Localita'": "RUVO DI PUGLIA",
  "Via": "VIA FRANCESCO SALOMONE ",
  "Civico": "36"
},
{
  "Denominazione": "HOUSE LA PALMA",
  "CIS": "BA07203891000021406",
  "Tipologia": "Alloggi privati",
  "Sottotipologia": "Locazione turistica",
  "Provincia": "BA",
  "Comune": "RUVO DI PUGLIA",
  "CAP": "70037",
  "Localita'": "Ruvo di Puglia",
  "Via": "via A. Moro",
  "Civico": "73"
},
{
  "Denominazione": "L'Orecchietta",
  "CIS": "BA07203891000001090",
  "Tipologia": "Alloggi privati",
  "Sottotipologia": "Locazione turistica",
  "Provincia": "BA",
  "Comune": "RUVO DI PUGLIA",
  "CAP": "70037",
  "Localita'": "Ruvo di Puglia",
  "Via": "Via Nello Rosselli",
  "Civico": "31"
},
{
  "Denominazione": "L'Orecchietta 2.0",
  "CIS": "BA07203891000001159",
  "Tipologia": "Alloggi privati",
  "Sottotipologia": "Locazione turistica",
  "Provincia": "BA",
  "Comune": "RUVO DI PUGLIA",
  "CAP": "70037",
  "Localita'": "Ruvo di Puglia",
  "Via": "Via le Monache",
  "Civico": "6"
},
{
  "Denominazione": "LA CASA IN FIORE",
  "CIS": "BA07203891000011118",
  "Tipologia": "Alloggi privati",
  "Sottotipologia": "Locazione turistica",
  "Provincia": "BA",
  "Comune": "RUVO DI PUGLIA",
  "CAP": "70037",
  "Via": "VIA G.AMENDOLA",
  "Civico": "38"
},
{
  "Denominazione": "La Vanella",
  "CIS": "BA07203891000014669",
  "Tipologia": "Alloggi privati",
  "Sottotipologia": "Locazione turistica",
  "Provincia": "BA",
  "Comune": "RUVO DI PUGLIA",
  "CAP": "70037",
  "Localita'": "Ruvo di Puglia",
  "Via": "via vanella gioberti ",
  "Civico": "13"
},
{
  "Denominazione": "MEDEA-Le dimore di Talos",
  "CIS": "BA07203891000017768",
  "Tipologia": "Alloggi privati",
  "Sottotipologia": "Locazione turistica",
  "Provincia": "BA",
  "Comune": "RUVO DI PUGLIA",
  "CAP": "70037",
  "Localita'": "ruvo di puglia ",
  "Via": "via cattedrale ",
  "Civico": "37"
},
{
  "Denominazione": "New home Orizzonte",
  "CIS": "BA07203891000036190",
  "Tipologia": "Alloggi privati",
  "Sottotipologia": "Locazione turistica",
  "Provincia": "BA",
  "Comune": "RUVO DI PUGLIA",
  "CAP": "70037",
  "Localita'": "Ruvo di Puglia ",
  "Via": "via Carlo Rosselli ",
  "Civico": "28"
},
{
  "Denominazione": "Torre Gigliano",
  "CIS": "BA07203891000008094",
  "Tipologia": "Alloggi privati",
  "Sottotipologia": "Locazione turistica",
  "Provincia": "BA",
  "Comune": "RUVO DI PUGLIA",
  "CAP": "70037",
  "Via": "Zona Rurale",
  "Civico": "24B"
},
{
  "Denominazione": "VIA BOLOGNESE",
  "CIS": "BA07203891000027696",
  "Tipologia": "Alloggi privati",
  "Sottotipologia": "Locazione turistica",
  "Provincia": "BA",
  "Comune": "RUVO DI PUGLIA",
  "CAP": "70037",
  "Via": "VIA BOLOGNESE",
  "Civico": "7"
},
{
  "Denominazione": "Villa Fenicia",
  "CIS": "BA07203891000024875",
  "Tipologia": "Alloggi privati",
  "Sottotipologia": "Locazione turistica",
  "Provincia": "BA",
  "Comune": "RUVO DI PUGLIA",
  "CAP": "70037",
  "Localita'": "collina",
  "Via": "zona rurale",
  "Civico": "24"
},
{
  "Denominazione": "antica ruvo apartment",
  "CIS": "BA07203891000008579",
  "Tipologia": "Alloggi privati",
  "Sottotipologia": "Locazione turistica",
  "Provincia": "BA",
  "Comune": "RUVO DI PUGLIA",
  "CAP": "70037",
  "Localita'": "ruvo di puglia",
  "Via": "via speranza ",
  "Civico": "15"
},
{
  "Denominazione": "attico Albamonte",
  "CIS": "BA07203891000029836",
  "Tipologia": "Alloggi privati",
  "Sottotipologia": "Locazione turistica",
  "Provincia": "BA",
  "Comune": "RUVO DI PUGLIA",
  "CAP": "70037",
  "Localita'": "Ruvo di Puglia",
  "Via": "via guglielmo albamonte",
  "Civico": "4"
},
{
  "Denominazione": "beb La Pigla",
  "CIS": "BA07203891000001388",
  "Tipologia": "Alloggi privati",
  "Sottotipologia": "Locazione turistica",
  "Provincia": "BA",
  "Comune": "RUVO DI PUGLIA",
  "CAP": "70037",
  "Via": "via nazario sauro ",
  "Civico": "131"
},
{
  "Denominazione": "casa Albamonte",
  "CIS": "BA07203891000029837",
  "Tipologia": "Alloggi privati",
  "Sottotipologia": "Locazione turistica",
  "Provincia": "BA",
  "Comune": "RUVO DI PUGLIA",
  "CAP": "70037",
  "Via": "via guglielmo albamonte di sicilia",
  "Civico": "4"
},
{
  "Denominazione": "casa Modesti",
  "CIS": "BA07203891000029853",
  "Tipologia": "Alloggi privati",
  "Sottotipologia": "Locazione turistica",
  "Provincia": "BA",
  "Comune": "RUVO DI PUGLIA",
  "CAP": "70037",
  "Localita'": "ruvo di puglia",
  "Via": "via modesti",
  "Civico": "17"
},
{
  "Denominazione": "casa vacanze Aldo Moro",
  "CIS": "BA07203891000032281",
  "Tipologia": "Alloggi privati",
  "Sottotipologia": "Locazione turistica",
  "Provincia": "BA",
  "Comune": "RUVO DI PUGLIA",
  "CAP": "70037",
  "Localita'": "comune di ruvo di puglia",
  "Via": "via Aldo Moro",
  "Civico": "2"
},
{
  "Denominazione": "le dimore di talos POSEIDONE",
  "CIS": "BA07203891000034192",
  "Tipologia": "Alloggi privati",
  "Sottotipologia": "Locazione turistica",
  "Provincia": "BA",
  "Comune": "RUVO DI PUGLIA",
  "CAP": "70037",
  "Localita'": "ruvo di puglia",
  "Via": "viaa avitaja ",
  "Civico": "28"
}
]
